firestone/__init__.py
firestone-0.0.1.dist-info/WHEEL
firestone-0.0.1.dist-info/METADATA
firestone-0.0.1.dist-info/RECORD
