Metadata-Version: 2.1
Name: firestone
Version: 0.0.1
Summary: Firestone
Home-page: https://bitbucket.org/jouwomgeving/firestone
License: UNKNOWN
Author: DK
Author-email: dkainama@jouwomgeving.nl
